truelayer_signing/__init__.py
truelayer_signing/crypto.py
truelayer_signing/errors.py
truelayer_signing/sign.py
truelayer_signing/utils.py
truelayer_signing/verify.py
truelayer_signing-0.3.7.dist-info/LICENSE-APACHE
truelayer_signing-0.3.7.dist-info/LICENSE-MIT
truelayer_signing-0.3.7.dist-info/METADATA
truelayer_signing-0.3.7.dist-info/WHEEL
truelayer_signing-0.3.7.dist-info/RECORD
