Metadata-Version: 2.3
Name: truelayer-signing
Version: 0.3.7
Summary: Produce & verify TrueLayer API requests signatures
License: Apache-2.0 or MIT
Keywords: truelayer
Author: tl-flavio-barinas
Author-email: flavio.barinas@truelayer.com
Requires-Python: >=3.8.1,<4.0.0
Classifier: License :: Other/Proprietary License
Classifier: Programming Language :: Python :: 3
Classifier: Programming Language :: Python :: 3.9
Classifier: Programming Language :: Python :: 3.10
Classifier: Programming Language :: Python :: 3.11
Classifier: Programming Language :: Python :: 3.12
Classifier: Programming Language :: Python :: 3.13
Requires-Dist: cryptography (>=39,<44)
Project-URL: Homepage, https://github.com/TrueLayer/truelayer-signing/tree/main/python
Project-URL: Repository, https://github.com/TrueLayer/truelayer-signing
